artur_owcz/__init__.py
artur_owcz/__main__.py
artur_owcz/names.txt
artur_owcz/speaker.py
artur_owcz/speakers/__init__.py
artur_owcz/speakers/artur.py
artur_owcz-0.3.0.dist-info/licenses/LICENSE.txt
artur_owcz-0.3.0.dist-info/METADATA
artur_owcz-0.3.0.dist-info/WHEEL
artur_owcz-0.3.0.dist-info/entry_points.txt
artur_owcz-0.3.0.dist-info/top_level.txt
artur_owcz-0.3.0.dist-info/RECORD
