Metadata-Version: 2.4
Name: artur_owcz
Version: 0.3.0
Summary: My first package!
Author-email: Artur Owczarek <owczarek.artur@gmail.com>
Maintainer-email: Artur Owczarek <owczarek.artur@gmail.com>
License: BSD 3-Clause License
Project-URL: Homepage, https://github.com/arturowczarek/arturowczarek
Project-URL: Documentation, https://github.com/arturowczarek/arturowczarek/README.md
Keywords: Owczarek
Classifier: Programming Language :: Python :: 3.9
Classifier: Programming Language :: Python :: Implementation :: CPython
Classifier: License :: OSI Approved :: BSD License
Classifier: Intended Audience :: Developers
Classifier: Operating System :: POSIX :: Linux
Classifier: Operating System :: Microsoft :: Windows
Classifier: Operating System :: MacOS
Classifier: Operating System :: MacOS :: MacOS X
Requires-Python: >=3.9
License-File: LICENSE.txt
Requires-Dist: colorama
Provides-Extra: dev
Requires-Dist: twine; extra == "dev"
Requires-Dist: build; extra == "dev"
Dynamic: license-file
